categories_i18n/__init__.py
categories_i18n/abstract_models.py
categories_i18n/admin.py
categories_i18n/apps.py
categories_i18n/managers.py
categories_i18n/models.py
categories_i18n/urls.py
categories_i18n/views.py
categories_i18n/migrations/0001_initial.py
categories_i18n/migrations/__init__.py
django_categories_i18n-2.0.dist-info/AUTHORS
django_categories_i18n-2.0.dist-info/LICENSE
django_categories_i18n-2.0.dist-info/METADATA
django_categories_i18n-2.0.dist-info/WHEEL
django_categories_i18n-2.0.dist-info/top_level.txt
django_categories_i18n-2.0.dist-info/RECORD
